datalint/__init__.py
datalint/cli.py
datalint/engine/__init__.py
datalint/engine/base.py
datalint/engine/learner.py
datalint/engine/profiler.py
datalint/engine/validators.py
datalint/utils/__init__.py
datalint/utils/io.py
datalint/utils/reporting.py
scripts/generate_diagrams.py
tests/__init__.py
tests/test_cli.py
tests/test_integration.py
tests/test_performance.py
tests/test_validators.py
datalint-0.1.0.dist-info/METADATA
datalint-0.1.0.dist-info/WHEEL
datalint-0.1.0.dist-info/entry_points.txt
datalint-0.1.0.dist-info/top_level.txt
datalint-0.1.0.dist-info/RECORD
