Metadata-Version: 2.4
Name: datalint
Version: 0.1.0
Summary: Automated data validation for ML teams
Author-email: DataLint Team <team@datalint.ai>
License: MIT
Project-URL: Homepage, https://github.com/STABLE-TURBO/datalint
Project-URL: Repository, https://github.com/STABLE-TURBO/datalint
Project-URL: Issues, https://github.com/STABLE-TURBO/datalint/issues
Project-URL: Documentation, https://datalint.readthedocs.io/
Classifier: Development Status :: 3 - Alpha
Classifier: Intended Audience :: Science/Research
Classifier: License :: OSI Approved :: MIT License
Classifier: Operating System :: OS Independent
Classifier: Programming Language :: Python :: 3
Classifier: Programming Language :: Python :: 3.8
Classifier: Programming Language :: Python :: 3.9
Classifier: Programming Language :: Python :: 3.10
Classifier: Programming Language :: Python :: 3.11
Classifier: Topic :: Scientific/Engineering :: Artificial Intelligence
Requires-Python: >=3.8
Requires-Dist: pandas==2.0.3
Requires-Dist: numpy==1.24.3
Requires-Dist: click==8.1.3
Requires-Dist: pyyaml==6.0
Requires-Dist: jinja2==3.1.2
Requires-Dist: openpyxl==3.1.2
Requires-Dist: scipy==1.10.1
